Metadata-Version: 2.1
Name: odoo-addon-fieldservice_vehicle_stock
Version: 15.0.1.0.0.3
Summary: Track inventory of Field Service vehicles
Home-page: https://github.com/OCA/field-service
Author: Open Source Integrators, Brian McMaster, Odoo Community Association (OCA)
Author-email: support@odoo-community.org
License: AGPL-3
Classifier: Programming Language :: Python
Classifier: Framework :: Odoo
Classifier: Framework :: Odoo :: 15.0
Classifier: License :: OSI Approved :: GNU Affero General Public License v3
Classifier: Development Status :: 4 - Beta
Requires-Python: >=3.8
Requires-Dist: odoo-addon-fieldservice-stock<15.1dev,>=15.0dev
Requires-Dist: odoo-addon-fieldservice-vehicle<15.1dev,>=15.0dev
Requires-Dist: odoo<15.1dev,>=15.0a
